ncbi-mcp/__init__.py
ncbi-mcp/efetch.py
ncbi-mcp/einfo.py
ncbi-mcp/esearch.py
ncbi-mcp/esummary.py
ncbi-mcp/server.py
ncbi_mcp/__init__.py
ncbi_mcp/efetch.py
ncbi_mcp/einfo.py
ncbi_mcp/esearch.py
ncbi_mcp/esummary.py
ncbi_mcp/server.py
ncbi_mcp-0.1.4.dist-info/METADATA
ncbi_mcp-0.1.4.dist-info/WHEEL
ncbi_mcp-0.1.4.dist-info/entry_points.txt
ncbi_mcp-0.1.4.dist-info/top_level.txt
ncbi_mcp-0.1.4.dist-info/RECORD
