Metadata-Version: 2.4
Name: ncbi-mcp
Version: 0.1.4
Summary: NCBI E-utilities MCP server for accessing NCBI databases
Home-page: https://github.com/QiGoki/ncbi-mcp
Author: goki
Author-email: goki <654051206@qq.com>
License-Expression: MIT
Project-URL: Homepage, https://github.com/QiGoki/ncbi-mcp
Classifier: Development Status :: 3 - Alpha
Classifier: Intended Audience :: Developers
Classifier: Intended Audience :: Science/Research
Classifier: Operating System :: OS Independent
Classifier: Programming Language :: Python :: 3.12
Requires-Python: >=3.8
Requires-Dist: requests>=2.25.0
Requires-Dist: python-dotenv>=0.19.0
Requires-Dist: mcp>=1.0.0
Dynamic: author
Dynamic: home-page
Dynamic: requires-python
